{"37.41.pkl": [[{"score": 34.793103448275865, "post": "average", "alg": "Pipeline(memory=None,\n     steps=[('decomp', None), ('standard', None), ('regressor', Pipeline(memory=None,\n     steps=[('poly', PolynomialFeatures(degree=2, include_bias=True, interaction_only=False)), ('regressor', HuberRegressor(alpha=0.0002, epsilon=1, fit_intercept=True, max_iter=100,\n        tol=1e-05, warm_start=False))]))])"}, {"average": [59.400000000000006, 34.793103448275865, 21.0], "ZScoreNormalized": [60.60000000000001, 39.6551724137931, 37.0], "PercentageNormalized": [64.20000000000002, 42.55172413793103, 45.0], "CouplesNormalized": [67.2, 38.793103448275865, 28.0]}], [{"score": 43.758620689655174, "post": "PercentageNormalized", "alg": "Pipeline(memory=None,\n     steps=[('decomp', None), ('standard', None), ('regressor', Pipeline(memory=None,\n     steps=[('poly', PolynomialFeatures(degree=2, include_bias=True, interaction_only=False)), ('regressor', HuberRegressor(alpha=0.0002, epsilon=1, fit_intercept=True, max_iter=100,\n        tol=1e-05, warm_start=False))]))])"}, {"average": [72.0, 45.3448275862069, 37.0], "ZScoreNormalized": [73.8, 49.03448275862069, 48.0], "PercentageNormalized": [61.2, 43.758620689655174, 43.0], "CouplesNormalized": [76.80000000000001, 47.37931034482759, 44.0]}], [{"score": 37.37931034482759, "post": "CouplesNormalized", "alg": "Pipeline(memory=None,\n     steps=[('decomp', None), ('standard', None), ('regressor', Pipeline(memory=None,\n     steps=[('poly', PolynomialFeatures(degree=2, include_bias=True, interaction_only=False)), ('regressor', HuberRegressor(alpha=0.0002, epsilon=1, fit_intercept=True, max_iter=100,\n        tol=1e-05, warm_start=False))]))])"}, {"average": [64.00000000000003, 37.827586206896555, 36.0], "ZScoreNormalized": [58.800000000000004, 39.689655172413794, 42.0], "PercentageNormalized": [63.60000000000001, 39.206896551724135, 43.0], "CouplesNormalized": [58.60000000000003, 37.37931034482759, 30.0]}], [{"score": 44.0, "post": "average", "alg": "Pipeline(memory=None,\n     steps=[('decomp', None), ('standard', None), ('regressor', Pipeline(memory=None,\n     steps=[('poly', PolynomialFeatures(degree=2, include_bias=True, interaction_only=False)), ('regressor', HuberRegressor(alpha=0.0002, epsilon=1, fit_intercept=True, max_iter=100,\n        tol=1e-05, warm_start=False))]))])"}, {"average": [62.800000000000004, 44.0, 50.0], "ZScoreNormalized": [79.0, 44.89655172413793, 40.0], "PercentageNormalized": [71.80000000000001, 46.06896551724138, 40.0], "CouplesNormalized": [72.4, 44.0, 41.0]}], [{"score": 37.13793103448276, "post": "average", "alg": "Pipeline(memory=None,\n     steps=[('decomp', None), ('standard', None), ('regressor', Pipeline(memory=None,\n     steps=[('poly', PolynomialFeatures(degree=2, include_bias=True, interaction_only=False)), ('regressor', HuberRegressor(alpha=0.0002, epsilon=1, fit_intercept=True, max_iter=100,\n        tol=1e-05, warm_start=False))]))])"}, {"average": [61.0, 37.13793103448276, 33.0], "ZScoreNormalized": [68.00000000000001, 45.206896551724135, 48.0], "PercentageNormalized": [74.4, 44.58620689655172, 42.0], "CouplesNormalized": [64.4, 38.827586206896555, 37.0]}]], "name": "37.41.pkl"}